utxorpc_spec/utxorpc/v1alpha/bitcoin/bitcoin_pb2.py
utxorpc_spec/utxorpc/v1alpha/bitcoin/bitcoin_pb2.pyi
utxorpc_spec/utxorpc/v1alpha/bitcoin/bitcoin_pb2_grpc.py
utxorpc_spec/utxorpc/v1alpha/cardano/cardano_pb2.py
utxorpc_spec/utxorpc/v1alpha/cardano/cardano_pb2.pyi
utxorpc_spec/utxorpc/v1alpha/cardano/cardano_pb2_grpc.py
utxorpc_spec/utxorpc/v1alpha/query/query_pb2.py
utxorpc_spec/utxorpc/v1alpha/query/query_pb2.pyi
utxorpc_spec/utxorpc/v1alpha/query/query_pb2_grpc.py
utxorpc_spec/utxorpc/v1alpha/submit/submit_pb2.py
utxorpc_spec/utxorpc/v1alpha/submit/submit_pb2.pyi
utxorpc_spec/utxorpc/v1alpha/submit/submit_pb2_grpc.py
utxorpc_spec/utxorpc/v1alpha/sync/sync_pb2.py
utxorpc_spec/utxorpc/v1alpha/sync/sync_pb2.pyi
utxorpc_spec/utxorpc/v1alpha/sync/sync_pb2_grpc.py
utxorpc_spec/utxorpc/v1alpha/watch/watch_pb2.py
utxorpc_spec/utxorpc/v1alpha/watch/watch_pb2.pyi
utxorpc_spec/utxorpc/v1alpha/watch/watch_pb2_grpc.py
utxorpc_spec-0.18.1.dist-info/METADATA
utxorpc_spec-0.18.1.dist-info/WHEEL
utxorpc_spec-0.18.1.dist-info/RECORD
