Metadata-Version: 2.4
Name: utxorpc-spec
Version: 0.18.1
Summary: Auto-generated structs for the UTxO RPC spec.
Author: Felipe Gonzalez
Author-email: felipe@txpipe.io
Requires-Python: >=3.9,<4.0
Classifier: Programming Language :: Python :: 3
Classifier: Programming Language :: Python :: 3.9
Classifier: Programming Language :: Python :: 3.10
Classifier: Programming Language :: Python :: 3.11
Classifier: Programming Language :: Python :: 3.12
Classifier: Programming Language :: Python :: 3.13
Classifier: Programming Language :: Python :: 3.14
Requires-Dist: grpc-stubs (>=1.53.0.6,<2.0.0.0)
Requires-Dist: grpcio (>=1.74,<2)
Requires-Dist: protobuf (>=6.32,<7)
Project-URL: Repository, https://github.com/utxorpc/spec
